PolyRound/__init__.py
PolyRound/api.py
PolyRound/default_settings.py
PolyRound/main.py
PolyRound/settings.py
PolyRound/unit_tests.py
PolyRound/mutable_classes/__init__.py
PolyRound/mutable_classes/polytope.py
PolyRound/static_classes/__init__.py
PolyRound/static_classes/constraint_removal_reduction.py
PolyRound/static_classes/csv_io.py
PolyRound/static_classes/lp_interfacing.py
PolyRound/static_classes/lp_utils.py
PolyRound/static_classes/parse_sbml_stoichiometry.py
PolyRound/static_classes/rounding/__init__.py
PolyRound/static_classes/rounding/geometric_mean_scaling.py
PolyRound/static_classes/rounding/maximum_volume_ellipsoid.py
PolyRound/static_classes/rounding/nearest_symmetric_positive_definite.py
polyround-0.4.0.dist-info/licenses/LICENSE
polyround-0.4.0.dist-info/METADATA
polyround-0.4.0.dist-info/WHEEL
polyround-0.4.0.dist-info/top_level.txt
polyround-0.4.0.dist-info/RECORD
