Metadata-Version: 2.4
Name: PolyRound
Version: 0.4.0
Summary: A python package for rounding polytopes.
Author-email: Axel Theorell <atheorell@ethz.ch>
License: GPL-3.0
Project-URL: Homepage, https://gitlab.com/csb.ethz/PolyRound
Project-URL: Bug Tracker, https://gitlab.com/csb.ethz/PolyRound/-/issues
Classifier: Development Status :: 4 - Beta
Classifier: Intended Audience :: Science/Research
Classifier: License :: OSI Approved :: GNU General Public License v3 (GPLv3)
Classifier: Programming Language :: Python :: 3
Classifier: Programming Language :: Python :: 3.8
Classifier: Programming Language :: Python :: 3.9
Classifier: Programming Language :: Python :: 3.10
Classifier: Programming Language :: Python :: 3.11
Classifier: Programming Language :: Python :: 3.12
Requires-Python: >=3.8
License-File: LICENSE
Requires-Dist: numpy>=1.2
Requires-Dist: pandas>=1.2
Requires-Dist: scipy>=1.4
Requires-Dist: optlang>=1.4
Provides-Extra: extras
Requires-Dist: cobra>=0.20; extra == "extras"
Requires-Dist: python-libsbml>=5.18; extra == "extras"
Requires-Dist: gurobipy; extra == "extras"
Dynamic: license-file
